LICENSE
MANIFEST.in
README
setup.py
lesscss/__init__.py
lesscss.egg-info/PKG-INFO
lesscss.egg-info/SOURCES.txt
lesscss.egg-info/dependency_links.txt
lesscss.egg-info/not-zip-safe
lesscss.egg-info/top_level.txt