Metadata-Version: 1.0
Name: lesscss
Version: 0.1.1
Summary: A helper which automatically compiles LESS files to CSS.
Home-page: http://github.com/faruken/lesscss
Author: Faruk Akgul
Author-email: me@akgul.org
License: BSD
Platform: any
Classifier: Environment :: Web Environment
Classifier: Intended Audience :: Developers
Classifier: License :: OSI Approved :: BSD License
Classifier: Operating System :: OS Independent
Classifier: Programming Language :: Python
Classifier: Programming Language :: Python :: 2.5
Classifier: Programming Language :: Python :: 2.6
Classifier: Programming Language :: Python :: 2.7
Classifier: Topic :: Internet :: WWW/HTTP :: Dynamic Content
Classifier: Topic :: Software Development :: Libraries :: Python Modules
